LICENSE.txt
README.md
pyproject.toml
setup.py
src/mob/MobException.py
src/mob/MobSecrets.py
src/mob/Module.py
src/mob/WorkDir.py
src/mob/__init__.py
src/mob/di.py
src/mob/AutoUpdate/AutoUpdateRepository.py
src/mob/AutoUpdate/AutoUpdateService.py
src/mob/AutoUpdate/CachedVersion.py
src/mob/AutoUpdate/PyPi.py
src/mob/AutoUpdate/VersionCheckerThread.py
src/mob/AutoUpdate/__init__.py
src/mob/Controllers/__init__.py
src/mob/Controllers/boostrap_cli_app.py
src/mob/Controllers/cli.py
src/mob/Controllers/done.py
src/mob/Controllers/next.py
src/mob/Controllers/start.py
src/mob/DotEnv/DotEnv.py
src/mob/DotEnv/__init__.py
src/mob/FileAccess/FileAccess.py
src/mob/FileAccess/__init__.py
src/mob/GitCli/BranchName.py
src/mob/GitCli/Exceptions.py
src/mob/GitCli/GitCliInterface.py
src/mob/GitCli/GitCliWithAutoRollback.py
src/mob/GitCli/Module.py
src/mob/GitCli/__init__.py
src/mob/GitCli/GitPython/GitCliWithGitPython.py
src/mob/GitCli/GitPython/GitLogHandler.py
src/mob/GitCli/GitPython/Module.py
src/mob/GitCli/GitPython/__init__.py
src/mob/GitCli/GitPython/GitActions/AddAll.py
src/mob/GitCli/GitPython/GitActions/AddEntryToInfoExclude.py
src/mob/GitCli/GitPython/GitActions/Checkout.py
src/mob/GitCli/GitPython/GitActions/Commit.py
src/mob/GitCli/GitPython/GitActions/ComposedGitActions.py
src/mob/GitCli/GitPython/GitActions/CreateHead.py
src/mob/GitCli/GitPython/GitActions/Exceptions.py
src/mob/GitCli/GitPython/GitActions/GitAction.py
src/mob/GitCli/GitPython/GitActions/Push.py
src/mob/GitCli/GitPython/GitActions/Reset.py
src/mob/GitCli/GitPython/GitActions/SquashAll.py
src/mob/GitCli/GitPython/GitActions/__init__.py
src/mob/GitCli/UndoCommands/ComposedUndoCommand.py
src/mob/GitCli/UndoCommands/UndoCallable.py
src/mob/GitCli/UndoCommands/UndoCommand.py
src/mob/GitCli/UndoCommands/__init__.py
src/mob/JsonSerializer/DataClassesSerializer.py
src/mob/JsonSerializer/Exceptions.py
src/mob/JsonSerializer/JsonSerializerInterface.py
src/mob/JsonSerializer/Module.py
src/mobt.egg-info/PKG-INFO
src/mobt.egg-info/SOURCES.txt
src/mobt.egg-info/dependency_links.txt
src/mobt.egg-info/entry_points.txt
src/mobt.egg-info/requires.txt
src/mobt.egg-info/top_level.txt