Metadata-Version: 2.1
Name: mobt
Version: 0.1.13
Summary: Mob session management tool
Home-page: https://github.com/stavarengo/mob
Author: rfst
Project-URL: Say Thanks!, https://saythanks.io/to/faelsta
Project-URL: Source, https://github.com/stavarengo/stavarengo/
Keywords: mob mob-programming timer mob-programming-timer cli-tool remote-mob-programming remote-mobs
Requires-Python: >=3.7
Provides-Extra: dev
License-File: LICENSE.txt
